todo_cli/__init__.py
todo_cli/__main__.py
todo_cli/cli.py
todo_cli/formatters.py
todo_cli/models.py
todo_cli/py.typed
todo_cli/repository.py
todo_cli/service.py
todo_cli_evolution-0.1.0.dist-info/METADATA
todo_cli_evolution-0.1.0.dist-info/WHEEL
todo_cli_evolution-0.1.0.dist-info/entry_points.txt
todo_cli_evolution-0.1.0.dist-info/RECORD
